MANIFEST.in
README.txt
setup.py
licenses/__init__.py
licenses/deploy.py
licenses/licenses.db
licenses/scrape.py
licenses/service.py
licenses/vocab.py
licenses.egg-info/PKG-INFO
licenses.egg-info/SOURCES.txt
licenses.egg-info/dependency_links.txt
licenses.egg-info/not-zip-safe
licenses.egg-info/top_level.txt