Metadata-Version: 1.0
Name: licenses
Version: 0.6
Summary: A list of open (http://opensource.org/, http://opendefinition.org/) licenses
Home-page: http://licenses.opendefinition.org/
Author: Open Knowledge Foundation
Author-email: info@okfn.org
License: Public Domain
Download-URL: http://bitbucket.org/okfn/licenses
Platform: UNKNOWN
